{"ball_start": [75, 75], "ball_end": [1200, 630], "ball": {"rect": {"x": 75, "y": 75, "w": 15, "h": 15}, "velocity": 0.0, "dir": {"x": 0.0, "y": 0.0}}, "objects": [{"inner": {"rect": {"x": 0, "y": 0, "w": 1280, "h": 30}}}, {"inner": {"rect": {"x": 0, "y": 690, "w": 1280, "h": 30}}}, {"inner": {"rect": {"x": 0, "y": 30, "w": 30, "h": 690}}}, {"inner": {"rect": {"x": 1250, "y": 30, "w": 30, "h": 720}}}, {"inner": {"rect": {"x": 1110, "y": 480, "w": 30, "h": 210}}}, {"inner": {"rect": {"x": 990, "y": 30, "w": 30, "h": 210}}}, {"inner": {"rect": {"x": 870, "y": 480, "w": 30, "h": 210}}}, {"inner": {"rect": {"x": 720, "y": 30, "w": 30, "h": 210}}}, {"inner": {"rect": {"x": 600, "y": 480, "w": 30, "h": 210}}}, {"inner": {"rect": {"x": 420, "y": 30, "w": 30, "h": 210}}}, {"inner": {"rect": {"x": 270, "y": 480, "w": 30, "h": 210}}}, {"inner": {"rect": {"x": 150, "y": 30, "w": 30, "h": 210}}}]}